README.md
setup.cfg
setup.py
cloudgenix_toolkit_spider/__init__.py
cloudgenix_toolkit_spider.egg-info/PKG-INFO
cloudgenix_toolkit_spider.egg-info/SOURCES.txt
cloudgenix_toolkit_spider.egg-info/dependency_links.txt
cloudgenix_toolkit_spider.egg-info/entry_points.txt
cloudgenix_toolkit_spider.egg-info/requires.txt
cloudgenix_toolkit_spider.egg-info/top_level.txt