Metadata-Version: 2.1
Name: cloudgenix-toolkit-spider
Version: 1.0.0
Summary: Utility to run commands/tests across large number of CloudGenix Toolkit instances.
Home-page: https://github.com/ebob9/cloudgenix_toolkit_spider
Author: Aaron Edwards
Author-email: cloudgenix_toolkit_spider@ebob9.com
License: MIT
Platform: UNKNOWN
Classifier: Development Status :: 4 - Beta
Classifier: Intended Audience :: Developers
Classifier: License :: OSI Approved :: MIT License
Classifier: Programming Language :: Python :: 2.7
Classifier: Programming Language :: Python :: 3
